vco_model.v
module vco_model(dig_ctrl_voltage, clk_vco);
    input wire [19:0] dig_ctrl_voltage;
    output reg clk_vco = 0;
    parameter VCO_CTRL_VOLTAGE_INC = 0.0000047684;
    parameter VCO_GAIN = 0.024;    
    parameter VCO_Fo = 0.095;
    
    integer write_data;

    real vco_freq = VCO_Fo;
    real vco_analog_ctrl_voltage = 0;
    real vco_period = 1/VCO_Fo;
    
    initial begin
        write_data = $fopen("/mnt/c/Users/kenny_h7nqsfc/Documents/gain_3000_150.csv");
    end

    always @(dig_ctrl_voltage) begin
        vco_analog_ctrl_voltage = dig_ctrl_voltage*VCO_CTRL_VOLTAGE_INC;
        vco_freq = VCO_Fo + vco_analog_ctrl_voltage*VCO_GAIN;
        vco_period = 1/vco_freq;
        $fdisplay(write_data, "%f,%f", vco_analog_ctrl_voltage, vco_period);
    end
    
    always #vco_period clk_vco = ~clk_vco;

endmodule

loop_filter.v
module loop_filter(clk, phase_error, dig_ctrl_voltage);

    parameter p_gain = 500;
    parameter i_gain = 100;

    // In out arguments

    input wire clk;
    input wire phase_error;
    output reg [19:0] dig_ctrl_voltage = 0;

    reg [31:0] proportional_out = 0;
    reg [31:0] integral_sum = 0;

    // Proportional path

    always @(posedge clk) begin
        proportional_out <= p_gain;
    end

    // Integral path

    always @(posedge clk) begin
        if(phase_error == 0) begin
            if (integral_sum > i_gain) begin
                integral_sum <= integral_sum - i_gain;
            end else begin
                integral_sum <=  integral_sum;
            end
        end else begin
            if(integral_sum == 1048576) begin
                integral_sum <= integral_sum;
            end else begin
                integral_sum <= integral_sum + i_gain;
            end
        end
    end

    always @(posedge clk) begin

        if (phase_error == 1) begin
            if(proportional_out + integral_sum > 1048576) begin
                dig_ctrl_voltage <= 1048576;
            end else begin
                dig_ctrl_voltage <= proportional_out + integral_sum;
            end
        end else begin
            dig_ctrl_voltage <= integral_sum;
            // if(integral_sum < proportional_out) begin
            //    dig_ctrl_voltage <= 0;
            ///end else begin
            //    dig_ctrl_voltage <= integral_sum - proportional_out;
            //end
        end
    end

endmodule

ff.v
`timescale 1ns / 1ps
//////////////////////////////////////////////////////////////////////////////////
// Company: 
// Engineer: 
// 
// Create Date: 10/04/2019 10:49:43 AM
// Design Name: 
// Module Name: ff
// Project Name: 
// Target Devices: 
// Tool Versions: 
// Description: 
// 
// Dependencies: 
// 
// Revision:
// Revision 0.01 - File Created
// Additional Comments:
// 
//////////////////////////////////////////////////////////////////////////////////


module ff
( input D,input cdn, input clk, output reg Q);
 
  always @ (posedge clk or negedge cdn) 
       if (!cdn)
          Q <= 0;
       else
          Q <= D;
endmodule

phase_detector.v
module phase_detector(f_ref, f_div, rst, dir);

    // The inputs

    input f_ref;  // The reference clock signal
    input f_div;  // The divided VCO signal
    input rst;  // A signal to reset the phase detection
    output dir; // Phase error output
    
    // flip-flops generating U and D

    wire U, D, CD;

    ff feed_back(1'b1,CD,f_ref,U);
    ff reference(1'b1,CD,f_div,D);

    assign CD = ~(~rst || (U && D));

    // logic to generate up and dn

    wire up, dn;

    assign up = (U && ~D); 
    assign dn = (~U && D);

    // logic to generate dir output

    wire dir_1, dir_2;

    nor (dir_1, up, dir_2);
    nor (dir_2, dn, dir_1); 

    assign dir = dir_2;
endmodule

pll_full_model.v
`timescale 1ns / 1ps

module pll_full_model();

    reg clk_master;
    wire clk_vco;    

    // Arguments for the phase detector

    reg rst;
    wire f_ref;
    wire f_div;
    wire dir;

    // Instantiate PD DUT
    
    assign f_ref = clk_master;
    assign f_div = clk_vco;

    phase_detector DUT_pd(.f_ref(f_ref), .f_div(f_div), .rst(rst), .dir(dir));

    // Arguments for the loop filter
    
    wire clk;
    wire phase_error;
    wire [19:0] dig_ctrl_voltage;
    // Instantiate LF DUT

    assign clk = clk_master;
    assign phase_error = dir;

    loop_filter #(3000,150) DUT_Lf(.clk(clk), .phase_error(phase_error), .dig_ctrl_voltage(dig_ctrl_voltage));

    // Instantiate VCO DUT

    vco_model DUT_vco(.dig_ctrl_voltage(dig_ctrl_voltage), .clk_vco(clk_vco));
    
    initial clk_master = 0;
    initial rst = 1;

    always #10 clk_master = ~clk_master;

    initial begin
        $dumpfile("pll_full_model.vcd");
        $dumpvars(0, pll_full_model);
        #100000 $finish;
    end

endmodule

pll_full_model.vcd
$date
	Fri Dec  6 22:02:27 2019
$end
$version
	Icarus Verilog
$end
$timescale
	1ps
$end
$scope module pll_full_model $end
$var wire 1 ! clk $end
$var wire 1 " f_div $end
$var wire 1 # f_ref $end
$var wire 1 $ phase_error $end
$var wire 1 % dir $end
$var wire 20 & dig_ctrl_voltage [19:0] $end
$var wire 1 ' clk_vco $end
$var reg 1 ( clk_master $end
$var reg 1 ) rst $end
$scope module DUT_Lf $end
$var wire 1 ! clk $end
$var wire 1 $ phase_error $end
$var reg 20 * dig_ctrl_voltage [19:0] $end
$var reg 32 + integral_sum [31:0] $end
$var reg 32 , proportional_out [31:0] $end
$upscope $end
$scope module DUT_pd $end
$var wire 1 - CD $end
$var wire 1 % dir $end
$var wire 1 . dir_1 $end
$var wire 1 / dir_2 $end
$var wire 1 0 dn $end
$var wire 1 " f_div $end
$var wire 1 # f_ref $end
$var wire 1 ) rst $end
$var wire 1 1 up $end
$var wire 1 2 U $end
$var wire 1 3 D $end
$scope module feed_back $end
$var wire 1 4 D $end
$var wire 1 - cdn $end
$var wire 1 # clk $end
$var reg 1 2 Q $end
$upscope $end
$scope module reference $end
$var wire 1 5 D $end
$var wire 1 - cdn $end
$var wire 1 " clk $end
$var reg 1 3 Q $end
$upscope $end
$upscope $end
$scope module DUT_vco $end
$var wire 20 6 dig_ctrl_voltage [19:0] $end
$var reg 1 ' clk_vco $end
$var real 1 7 vco_analog_ctrl_voltage $end
$var real 1 8 vco_freq $end
$var real 1 9 vco_period $end
$var integer 32 : write_data [31:0] $end
$upscope $end
$upscope $end
$enddefinitions $end
#0
$dumpvars
b10 :
r10.52631578947368 9
r0.095 8
r0 7
b0 6
15
14
x3
x2
x1
x0
x/
x.
x-
b0 ,
b0 +
b0 *
1)
0(
0'
b0 &
x%
x$
0#
0"
0!
$end
#10000
00
b101110111000 ,
b10010110 +
12
1!
1#
1(
#10526
02
1-
01
03
1"
1'
#20000
0!
0#
0(
#21052
0"
0'
#30000
1$
1%
1/
0.
r10.5244140566573 9
r0.09501716624000001 8
r0.00071526 7
11
b10010110 &
b10010110 *
b10010110 6
b100101100 +
12
1!
1#
1(
#31578
02
1-
01
03
1"
1'
#40000
0!
0#
0(
#42102
0"
0'
#50000
r10.48463579960139 9
r0.09537765728 8
r0.01573572 7
11
b111000010 +
b110011100100 &
b110011100100 *
b110011100100 6
12
1!
1#
1(
#52626
02
1-
01
03
1"
1'
#60000
0!
0#
0(
#63111
0"
0'
#70000
r10.48274909581802 9
r0.09539482352 8
r0.01645098 7
11
b110101111010 &
b110101111010 *
b110101111010 6
b1001011000 +
12
1!
1#
1(
#73596
02
1-
01
03
1"
1'
#80000
0!
0#
0(
#84079
0"
0'
#90000
r10.48086307093487 9
r0.09541198976 8
r0.01716624 7
11
b1011101110 +
b111000010000 &
b111000010000 *
b111000010000 6
12
1!
1#
1(
#94562
02
1-
01
03
1"
1'
#100000
0!
0#
0(
#105043
0"
0'
#110000
r10.47897772458555 9
r0.095429156 8
r0.0178815 7
11
b111010100110 &
b111010100110 *
b111010100110 6
b1110000100 +
12
1!
1#
1(
#115524
02
1-
01
03
1"
1'
#120000
0!
0#
0(
#126003
0"
0'
#130000
r10.47709305640397 9
r0.09544632224000001 8
r0.01859676 7
11
b10000011010 +
b111100111100 &
b111100111100 *
b111100111100 6
12
1!
1#
1(
#136482
02
1-
01
03
1"
1'
#140000
0!
0#
0(
#146959
0"
0'
#150000
r10.47520906602428 9
r0.09546348848 8
r0.01931202 7
11
b111111010010 &
b111111010010 *
b111111010010 6
b10010110000 +
12
1!
1#
1(
#157436
02
1-
01
03
1"
1'
#160000
0!
0#
0(
#167911
0"
0'
#170000
r10.47332575308089 9
r0.09548065472 8
r0.02002728 7
11
b10101000110 +
b1000001101000 &
b1000001101000 *
b1000001101000 6
12
1!
1#
1(
#178386
02
1-
01
03
1"
1'
#180000
0!
0#
0(
#188859
0"
0'
#190000
r10.47144311720848 9
r0.09549782096000001 8
r0.02074254 7
11
b1000011111110 &
b1000011111110 *
b1000011111110 6
b10111011100 +
12
1!
1#
1(
#199332
02
1-
01
03
1"
1'
#200000
0!
0#
0(
#209803
0"
0'
#210000
r10.46956115804201 9
r0.0955149872 8
r0.0214578 7
11
b11001110010 +
b1000110010100 &
b1000110010100 *
b1000110010100 6
12
1!
1#
1(
#220000
0!
0#
0(
#220274
02
1-
01
03
1"
1'
#230000
r10.46767987521668 9
r0.09553215344 8
r0.02217306 7
11
b1001000101010 &
b1001000101010 *
b1001000101010 6
b11100001000 +
12
1!
1#
1(
#230744
0"
0'
#240000
0!
0#
0(
#241212
02
1-
01
03
1"
1'
#250000
r10.46579926836796 9
r0.09554931967999999 8
r0.02288832 7
11
b11110011110 +
b1001011000000 &
b1001011000000 *
b1001011000000 6
12
1!
1#
1(
#251680
0"
0'
#260000
0!
0#
0(
#262146
02
1-
01
03
1"
1'
#270000
r10.46391933713157 9
r0.09556648592 8
r0.02360358 7
11
b1001101010110 &
b1001101010110 *
b1001101010110 6
b100000110100 +
12
1!
1#
1(
#272612
0"
0'
#280000
0!
0#
0(
#283076
02
1-
01
03
1"
1'
#290000
r10.46204008114352 9
r0.09558365216 8
r0.02431884 7
11
b100011001010 +
b1001111101100 &
b1001111101100 *
b1001111101100 6
12
1!
1#
1(
#293540
0"
0'
#300000
0!
0#
0(
#304002
02
1-
01
03
1"
1'
#310000
r10.46016150004005 9
r0.0956008184 8
r0.0250341 7
11
b1010010000010 &
b1010010000010 *
b1010010000010 6
b100101100000 +
12
1!
1#
1(
#314464
0"
0'
#320000
0!
0#
0(
#324924
02
1-
01
03
1"
1'
#330000
r10.45828359345768 9
r0.09561798464 8
r0.02574936 7
11
b100111110110 +
b1010100011000 &
b1010100011000 *
b1010100011000 6
12
1!
1#
1(
#335384
0"
0'
#340000
0!
0#
0(
#345842
02
1-
01
03
1"
1'
#350000
r10.45640636103318 9
r0.09563515088000001 8
r0.02646462 7
11
b1010110101110 &
b1010110101110 *
b1010110101110 6
b101010001100 +
12
1!
1#
1(
#356300
0"
0'
#360000
0!
0#
0(
#366756
02
1-
01
03
1"
1'
#370000
r10.4545298024036 9
r0.09565231712 8
r0.02717988 7
11
b101100100010 +
b1011001000100 &
b1011001000100 *
b1011001000100 6
12
1!
1#
1(
#377212
0"
0'
#380000
0!
0#
0(
#387667
02
1-
01
03
1"
1'
#390000
r10.45265391720623 9
r0.09566948336 8
r0.02789514 7
11
b1011011011010 &
b1011011011010 *
b1011011011010 6
b101110111000 +
12
1!
1#
1(
#398122
0"
0'
#400000
0!
0#
0(
#408575
02
1-
01
03
1"
1'
#410000
r10.45077870507862 9
r0.09568664960000001 8
r0.0286104 7
11
b110001001110 +
b1011101110000 &
b1011101110000 *
b1011101110000 6
12
1!
1#
1(
#419028
0"
0'
#420000
0!
0#
0(
#429479
02
1-
01
03
1"
1'
#430000
r10.44890416565861 9
r0.09570381584 8
r0.02932566 7
11
b1100000000110 &
b1100000000110 *
b1100000000110 6
b110011100100 +
12
1!
1#
1(
#439930
0"
0'
#440000
0!
0#
0(
#450000
r10.44703029858425 9
r0.09572098208 8
r0.03004092 7
b110101111010 +
b1100010011100 &
b1100010011100 *
b1100010011100 6
1!
1#
1(
#450379
02
1-
01
03
1"
1'
#460000
0!
0#
0(
#460826
0"
0'
#470000
r10.44515710349389 9
r0.09573814832000001 8
r0.03075618 7
11
b1100100110010 &
b1100100110010 *
b1100100110010 6
b111000010000 +
12
1!
1#
1(
#471273
02
1-
01
03
1"
1'
#480000
0!
0#
0(
#481718
0"
0'
#490000
r10.44328458002613 9
r0.09575531456 8
r0.03147144 7
11
b111010100110 +
b1100111001000 &
b1100111001000 *
b1100111001000 6
12
1!
1#
1(
#492163
02
1-
01
03
1"
1'
#500000
0!
0#
0(
#502606
0"
0'
#510000
r10.44141272781983 9
r0.0957724808 8
r0.0321867 7
11
b1101001011110 &
b1101001011110 *
b1101001011110 6
b111100111100 +
12
1!
1#
1(
#513049
02
1-
01
03
1"
1'
#520000
0!
0#
0(
#523490
0"
0'
#530000
r10.43954154651409 9
r0.09578964703999999 8
r0.03290196 7
11
b111111010010 +
b1101011110100 &
b1101011110100 *
b1101011110100 6
12
1!
1#
1(
#533931
02
1-
01
03
1"
1'
#540000
0!
0#
0(
#544371
0"
0'
#550000
r10.43767103574828 9
r0.09580681328 8
r0.03361722 7
11
b1101110001010 &
b1101110001010 *
b1101110001010 6
b1000001101000 +
12
1!
1#
1(
#554811
02
1-
01
03
1"
1'
#560000
0!
0#
0(
#565249
0"
0'
#570000
r10.43580119516205 9
r0.09582397952 8
r0.03433248 7
11
b1000011111110 +
b1110000100000 &
b1110000100000 *
b1110000100000 6
12
1!
1#
1(
#575687
02
1-
01
03
1"
1'
#580000
0!
0#
0(
#586123
0"
0'
#590000
r10.43393202439528 9
r0.09584114576 8
r0.03504774 7
11
b1110010110110 &
b1110010110110 *
b1110010110110 6
b1000110010100 +
12
1!
1#
1(
#596559
02
1-
01
03
1"
1'
#600000
0!
0#
0(
#606993
0"
0'
#610000
r10.43206352308812 9
r0.095858312 8
r0.035763 7
11
b1001000101010 +
b1110101001100 &
b1110101001100 *
b1110101001100 6
12
1!
1#
1(
#617427
02
1-
01
03
1"
1'
#620000
0!
0#
0(
#627859
0"
0'
#630000
r10.43019569088097 9
r0.09587547824000001 8
r0.03647826 7
11
b1110111100010 &
b1110111100010 *
b1110111100010 6
b1001011000000 +
12
1!
1#
1(
#638291
02
1-
01
03
1"
1'
#640000
0!
0#
0(
#648721
0"
0'
#650000
r10.42832852741449 9
r0.09589264448 8
r0.03719352 7
11
b1001101010110 +
b1111001111000 &
b1111001111000 *
b1111001111000 6
12
1!
1#
1(
#659151
02
1-
01
03
1"
1'
#660000
0!
0#
0(
#669579
0"
0'
#670000
r10.42646203232962 9
r0.09590981072 8
r0.03790878 7
11
b1111100001110 &
b1111100001110 *
b1111100001110 6
b1001111101100 +
12
1!
1#
1(
#680000
0!
0#
0(
#680007
02
1-
01
03
1"
1'
#690000
r10.42459620526751 9
r0.09592697696000001 8
r0.03862404 7
11
b1010010000010 +
b1111110100100 &
b1111110100100 *
b1111110100100 6
12
1!
1#
1(
#690433
0"
0'
#700000
0!
0#
0(
#700858
02
1-
01
03
1"
1'
#710000
r10.42273104586961 9
r0.0959441432 8
r0.0393393 7
11
b10000000111010 &
b10000000111010 *
b10000000111010 6
b1010100011000 +
12
1!
1#
1(
#711283
0"
0'
#720000
0!
0#
0(
#721706
02
1-
01
03
1"
1'
#730000
r10.42086655377761 9
r0.09596130944 8
r0.04005456 7
11
b1010110101110 +
b10000011010000 &
b10000011010000 *
b10000011010000 6
12
1!
1#
1(
#732129
0"
0'
#740000
0!
0#
0(
#742550
02
1-
01
03
1"
1'
#750000
r10.41900272863346 9
r0.09597847567999999 8
r0.04076982 7
11
b10000101100110 &
b10000101100110 *
b10000101100110 6
b1011001000100 +
12
1!
1#
1(
#752971
0"
0'
#760000
0!
0#
0(
#763390
02
1-
01
03
1"
1'
#770000
r10.41713957007935 9
r0.09599564192 8
r0.04148508 7
11
b1011011011010 +
b10000111111100 &
b10000111111100 *
b10000111111100 6
12
1!
1#
1(
#773809
0"
0'
#780000
0!
0#
0(
#784226
02
1-
01
03
1"
1'
#790000
r10.41527707775775 9
r0.09601280816 8
r0.04220034 7
11
b10001010010010 &
b10001010010010 *
b10001010010010 6
b1011101110000 +
12
1!
1#
1(
#794643
0"
0'
#800000
0!
0#
0(
#805058
02
1-
01
03
1"
1'
#810000
r10.41341525131137 9
r0.0960299744 8
r0.0429156 7
11
b1100000000110 +
b10001100101000 &
b10001100101000 *
b10001100101000 6
12
1!
1#
1(
#815473
0"
0'
#820000
0!
0#
0(
#825886
02
1-
01
03
1"
1'
#830000
r10.41155409038317 9
r0.09604714064 8
r0.04363086 7
11
b10001110111110 &
b10001110111110 *
b10001110111110 6
b1100010011100 +
12
1!
1#
1(
#836299
0"
0'
#840000
0!
0#
0(
#846711
02
1-
01
03
1"
1'
#850000
r10.4096935946164 9
r0.09606430688000001 8
r0.04434612 7
11
b1100100110010 +
b10010001010100 &
b10010001010100 *
b10010001010100 6
12
1!
1#
1(
#857123
0"
0'
#860000
0!
0#
0(
#867533
02
1-
01
03
1"
1'
#870000
r10.40783376365452 9
r0.09608147312 8
r0.04506138 7
11
b10010011101010 &
b10010011101010 *
b10010011101010 6
b1100111001000 +
12
1!
1#
1(
#877943
0"
0'
#880000
0!
0#
0(
#888351
02
1-
01
03
1"
1'
#890000
r10.40597459714127 9
r0.09609863936 8
r0.04577664 7
11
b1101001011110 +
b10010110000000 &
b10010110000000 *
b10010110000000 6
12
1!
1#
1(
#898759
0"
0'
#900000
0!
0#
0(
#909165
02
1-
01
03
1"
1'
#910000
r10.40411609472064 9
r0.09611580560000001 8
r0.0464919 7
11
b10011000010110 &
b10011000010110 *
b10011000010110 6
b1101011110100 +
12
1!
1#
1(
#919571
0"
0'
#920000
0!
0#
0(
#929975
02
1-
01
03
1"
1'
#930000
r10.40225825603687 9
r0.09613297184 8
r0.04720716 7
11
b1101110001010 +
b10011010101100 &
b10011010101100 *
b10011010101100 6
12
1!
1#
1(
#940000
0!
0#
0(
#940379
0"
0'
#950000
r10.40040108073446 9
r0.09615013808 8
r0.04792242 7
b10011101000010 &
b10011101000010 *
b10011101000010 6
b1110000100000 +
1!
1#
1(
#950781
02
1-
01
03
1"
1'
#960000
0!
0#
0(
#961181
0"
0'
#970000
r10.39854456845817 9
r0.09616730432000001 8
r0.04863768 7
11
b1110010110110 +
b10011111011000 &
b10011111011000 *
b10011111011000 6
12
1!
1#
1(
#971581
02
1-
01
03
1"
1'
#980000
0!
0#
0(
#981980
0"
0'
#990000
r10.39668871885299 9
r0.09618447056 8
r0.04935294 7
11
b10100001101110 &
b10100001101110 *
b10100001101110 6
b1110101001100 +
12
1!
1#
1(
#992379
02
1-
01
03
1"
1'
#1000000
0!
0#
0(
#1002776
0"
0'
#1010000
r10.39483353156419 9
r0.0962016368 8
r0.0500682 7
11
b1110111100010 +
b10100100000100 &
b10100100000100 *
b10100100000100 6
12
1!
1#
1(
#1013173
02
1-
01
03
1"
1'
#1020000
0!
0#
0(
#1023568
0"
0'
#1030000
r10.39297900623728 9
r0.09621880303999999 8
r0.05078346 7
11
b10100110011010 &
b10100110011010 *
b10100110011010 6
b1111001111000 +
12
1!
1#
1(
#1033963
02
1-
01
03
1"
1'
#1040000
0!
0#
0(
#1044356
0"
0'
#1050000
r10.39112514251802 9
r0.09623596928 8
r0.05149872 7
11
b1111100001110 +
b10101000110000 &
b10101000110000 *
b10101000110000 6
12
1!
1#
1(
#1054749
02
1-
01
03
1"
1'
#1060000
0!
0#
0(
#1065140
0"
0'
#1070000
r10.38927194005243 9
r0.09625313552 8
r0.05221398 7
11
b10101011000110 &
b10101011000110 *
b10101011000110 6
b1111110100100 +
12
1!
1#
1(
#1075531
02
1-
01
03
1"
1'
#1080000
0!
0#
0(
#1085920
0"
0'
#1090000
r10.38741939848678 9
r0.09627030176 8
r0.05292924 7
11
b10000000111010 +
b10101101011100 &
b10101101011100 *
b10101101011100 6
12
1!
1#
1(
#1096309
02
1-
01
03
1"
1'
#1100000
0!
0#
0(
#1106696
0"
0'
#1110000
r10.38556751746759 9
r0.096287468 8
r0.0536445 7
11
b10101111110010 &
b10101111110010 *
b10101111110010 6
b10000011010000 +
12
1!
1#
1(
#1117083
02
1-
01
03
1"
1'
#1120000
0!
0#
0(
#1127469
0"
0'
#1130000
r10.38371629664163 9
r0.09630463424000001 8
r0.05435976 7
11
b10000101100110 +
b10110010001000 &
b10110010001000 *
b10110010001000 6
12
1!
1#
1(
#1137855
02
1-
01
03
1"
1'
#1140000
0!
0#
0(
#1148239
0"
0'
#1150000
r10.38186573565594 9
r0.09632180048 8
r0.05507502 7
11
b10110100011110 &
b10110100011110 *
b10110100011110 6
b10000111111100 +
12
1!
1#
1(
#1158623
02
1-
01
03
1"
1'
#1160000
0!
0#
0(
#1169005
0"
0'
#1170000
r10.38001583415779 9
r0.09633896672 8
r0.05579028 7
11
b10001010010010 +
b10110110110100 &
b10110110110100 *
b10110110110100 6
12
1!
1#
1(
#1179387
02
1-
01
03
1"
1'
#1180000
0!
0#
0(
#1189767
0"
0'
#1190000
r10.3781665917947 9
r0.09635613296000001 8
r0.05650554 7
11
b10111001001010 &
b10111001001010 *
b10111001001010 6
b10001100101000 +
12
1!
1#
1(
#1200000
0!
0#
0(
#1200147
02
1-
01
03
1"
1'
#1210000
r10.37631800821446 9
r0.0963732992 8
r0.0572208 7
11
b10001110111110 +
b10111011100000 &
b10111011100000 *
b10111011100000 6
12
1!
1#
1(
#1210525
0"
0'
#1220000
0!
0#
0(
#1220901
02
1-
01
03
1"
1'
#1230000
r10.37447008306509 9
r0.09639046544 8
r0.05793606 7
11
b10111101110110 &
b10111101110110 *
b10111101110110 6
b10010001010100 +
12
1!
1#
1(
#1231277
0"
0'
#1240000
0!
0#
0(
#1241651
02
1-
01
03
1"
1'
#1250000
r10.37262281599489 9
r0.09640763167999999 8
r0.05865132 7
11
b10010011101010 +
b11000000001100 &
b11000000001100 *
b11000000001100 6
12
1!
1#
1(
#1252025
0"
0'
#1260000
0!
0#
0(
#1262398
02
1-
01
03
1"
1'
#1270000
r10.37077620665238 9
r0.09642479792 8
r0.05936658 7
11
b11000010100010 &
b11000010100010 *
b11000010100010 6
b10010110000000 +
12
1!
1#
1(
#1272771
0"
0'
#1280000
0!
0#
0(
#1283142
02
1-
01
03
1"
1'
#1290000
r10.36893025468634 9
r0.09644196416 8
r0.06008184 7
11
b10011000010110 +
b11000100111000 &
b11000100111000 *
b11000100111000 6
12
1!
1#
1(
#1293513
0"
0'
#1300000
0!
0#
0(
#1303882
02
1-
01
03
1"
1'
#1310000
r10.36708495974581 9
r0.0964591304 8
r0.0607971 7
11
b11000111001110 &
b11000111001110 *
b11000111001110 6
b10011010101100 +
12
1!
1#
1(
#1314251
0"
0'
#1320000
0!
0#
0(
#1324618
02
1-
01
03
1"
1'
#1330000
r10.36524032148007 9
r0.09647629664 8
r0.06151236 7
11
b10011101000010 +
b11001001100100 &
b11001001100100 *
b11001001100100 6
12
1!
1#
1(
#1334985
0"
0'
#1340000
0!
0#
0(
#1345350
02
1-
01
03
1"
1'
#1350000
r10.36339633953864 9
r0.09649346288000001 8
r0.06222762 7
11
b11001011111010 &
b11001011111010 *
b11001011111010 6
b10011111011000 +
12
1!
1#
1(
#1355715
0"
0'
#1360000
0!
0#
0(
#1366078
02
1-
01
03
1"
1'
#1370000
r10.36155301357132 9
r0.09651062912 8
r0.06294287999999999 7
11
b10100001101110 +
b11001110010000 &
b11001110010000 *
b11001110010000 6
12
1!
1#
1(
#1376441
0"
0'
#1380000
0!
0#
0(
#1386803
02
1-
01
03
1"
1'
#1390000
r10.35971034322813 9
r0.09652779536 8
r0.06365814 7
11
b11010000100110 &
b11010000100110 *
b11010000100110 6
b10100100000100 +
12
1!
1#
1(
#1397165
0"
0'
#1400000
0!
0#
0(
#1407525
02
1-
01
03
1"
1'
#1410000
r10.35786832815934 9
r0.09654496160000001 8
r0.0643734 7
11
b10100110011010 +
b11010010111100 &
b11010010111100 *
b11010010111100 6
12
1!
1#
1(
#1417885
0"
0'
#1420000
0!
0#
0(
#1428243
02
1-
01
03
1"
1'
#1430000
r10.3560269680155 9
r0.09656212784 8
r0.06508865999999999 7
11
b11010101010010 &
b11010101010010 *
b11010101010010 6
b10101000110000 +
12
1!
1#
1(
#1438601
0"
0'
#1440000
0!
0#
0(
#1448957
02
1-
01
03
1"
1'
#1450000
r10.35418626244736 9
r0.09657929408 8
r0.06580392 7
11
b10101011000110 +
b11010111101000 &
b11010111101000 *
b11010111101000 6
12
1!
1#
1(
#1459313
0"
0'
#1460000
0!
0#
0(
#1469667
02
1-
01
03
1"
1'
#1470000
r10.35234621110597 9
r0.09659646032000001 8
r0.06651918 7
11
b11011001111110 &
b11011001111110 *
b11011001111110 6
b10101101011100 +
12
1!
1#
1(
#1480000
0!
0#
0(
#1480021
0"
0'
#1490000
r10.35050681364258 9
r0.09661362656 8
r0.06723443999999999 7
b10101111110010 +
b11011100010100 &
b11011100010100 *
b11011100010100 6
1!
1#
1(
#1490373
02
1-
01
03
1"
1'
#1500000
0!
0#
0(
#1500724
0"
0'
#1510000
r10.34866806970873 9
r0.0966307928 8
r0.0679497 7
11
b11011110101010 &
b11011110101010 *
b11011110101010 6
b10110010001000 +
12
1!
1#
1(
#1511075
02
1-
01
03
1"
1'
#1520000
0!
0#
0(
#1521424
0"
0'
#1530000
r10.34682997895617 9
r0.09664795903999999 8
r0.06866496 7
11
b10110100011110 +
b11100001000000 &
b11100001000000 *
b11100001000000 6
12
1!
1#
1(
#1531773
02
1-
01
03
1"
1'
#1540000
0!
0#
0(
#1542120
0"
0'
#1550000
r10.34499254103693 9
r0.09666512528 8
r0.06938021999999999 7
11
b11100011010110 &
b11100011010110 *
b11100011010110 6
b10110110110100 +
12
1!
1#
1(
#1552467
02
1-
01
03
1"
1'
#1560000
0!
0#
0(
#1562812
0"
0'
#1570000
r10.34315575560326 9
r0.09668229152 8
r0.07009548 7
11
b10111001001010 +
b11100101101100 &
b11100101101100 *
b11100101101100 6
12
1!
1#
1(
#1573157
02
1-
01
03
1"
1'
#1580000
0!
0#
0(
#1583500
0"
0'
#1590000
r10.34131962230767 9
r0.09669945776 8
r0.07081074 7
11
b11101000000010 &
b11101000000010 *
b11101000000010 6
b10111011100000 +
12
1!
1#
1(
#1593843
02
1-
01
03
1"
1'
#1600000
0!
0#
0(
#1604184
0"
0'
#1610000
r10.33948414080293 9
r0.096716624 8
r0.07152599999999999 7
11
b10111101110110 +
b11101010011000 &
b11101010011000 *
b11101010011000 6
12
1!
1#
1(
#1614525
02
1-
01
03
1"
1'
#1620000
0!
0#
0(
#1624864
0"
0'
#1630000
r10.33764931074203 9
r0.09673379024000001 8
r0.07224126 7
11
b11101100101110 &
b11101100101110 *
b11101100101110 6
b11000000001100 +
12
1!
1#
1(
#1635203
02
1-
01
03
1"
1'
#1640000
0!
0#
0(
#1645541
0"
0'
#1650000
r10.33581513177822 9
r0.09675095648 8
r0.07295652 7
11
b11000010100010 +
b11101111000100 &
b11101111000100 *
b11101111000100 6
12
1!
1#
1(
#1655879
02
1-
01
03
1"
1'
#1660000
0!
0#
0(
#1666215
0"
0'
#1670000
r10.333981603565 9
r0.09676812272 8
r0.07367178000000001 7
11
b11110001011010 &
b11110001011010 *
b11110001011010 6
b11000100111000 +
12
1!
1#
1(
#1676551
02
1-
01
03
1"
1'
#1680000
0!
0#
0(
#1686885
0"
0'
#1690000
r10.3321487257561 9
r0.09678528896000001 8
r0.07438704 7
11
b11000111001110 +
b11110011110000 &
b11110011110000 *
b11110011110000 6
12
1!
1#
1(
#1697219
02
1-
01
03
1"
1'
#1700000
0!
0#
0(
#1707551
0"
0'
#1710000
r10.33031649800552 9
r0.0968024552 8
r0.0751023 7
11
b11110110000110 &
b11110110000110 *
b11110110000110 6
b11001001100100 +
12
1!
1#
1(
#1717883
02
1-
01
03
1"
1'
#1720000
0!
0#
0(
#1728213
0"
0'
#1730000
r10.32848491996748 9
r0.09681962144 8
r0.07581756000000001 7
11
b11001011111010 +
b11111000011100 &
b11111000011100 *
b11111000011100 6
12
1!
1#
1(
#1738543
02
1-
01
03
1"
1'
#1740000
0!
0#
0(
#1748871
0"
0'
#1750000
r10.32665399129646 9
r0.09683678767999999 8
r0.07653282 7
11
b11111010110010 &
b11111010110010 *
b11111010110010 6
b11001110010000 +
12
1!
1#
1(
#1759199
02
1-
01
03
1"
1'
#1760000
0!
0#
0(
#1769526
0"
0'
#1770000
r10.32482371164719 9
r0.09685395392 8
r0.07724808 7
11
b11010000100110 +
b11111101001000 &
b11111101001000 *
b11111101001000 6
12
1!
1#
1(
#1779853
02
1-
01
03
1"
1'
#1780000
0!
0#
0(
#1790000
r10.32299408067462 9
r0.09687112016 8
r0.07796334000000001 7
11
b11111111011110 &
b11111111011110 *
b11111111011110 6
b11010010111100 +
12
1!
1#
1(
#1790178
0"
0'
#1800000
0!
0#
0(
#1800501
02
1-
01
03
1"
1'
#1810000
r10.32116509803398 9
r0.0968882864 8
r0.0786786 7
11
b11010101010010 +
b100000001110100 &
b100000001110100 *
b100000001110100 6
12
1!
1#
1(
#1810824
0"
0'
#1820000
0!
0#
0(
#1821145
02
1-
01
03
1"
1'
#1830000
r10.31933676338071 9
r0.09690545264 8
r0.07939386 7
11
b100000100001010 &
b100000100001010 *
b100000100001010 6
b11010111101000 +
12
1!
1#
1(
#1831466
0"
0'
#1840000
0!
0#
0(
#1841785
02
1-
01
03
1"
1'
#1850000
r10.31750907637051 9
r0.09692261888000001 8
r0.08010912000000001 7
11
b11011001111110 +
b100000110100000 &
b100000110100000 *
b100000110100000 6
12
1!
1#
1(
#1852104
0"
0'
#1860000
0!
0#
0(
#1862422
02
1-
01
03
1"
1'
#1870000
r10.31568203665934 9
r0.09693978512 8
r0.08082438 7
11
b100001000110110 &
b100001000110110 *
b100001000110110 6
b11011100010100 +
12
1!
1#
1(
#1872740
0"
0'
#1880000
0!
0#
0(
#1883056
02
1-
01
03
1"
1'
#1890000
r10.31385564390336 9
r0.09695695136 8
r0.08153964 7
11
b11011110101010 +
b100001011001100 &
b100001011001100 *
b100001011001100 6
12
1!
1#
1(
#1893372
0"
0'
#1900000
0!
0#
0(
